tgzr/shell/__init__.py
tgzr/shell/_version.py
tgzr/shell/app.py
tgzr/shell/base_config.py
tgzr/shell/broker.py
tgzr/shell/connection.py
tgzr/shell/project.py
tgzr/shell/services.py
tgzr/shell/session.py
tgzr/shell/settings.py
tgzr/shell/studio.py
tgzr/shell/system.py
tgzr/shell/workspace.py
tgzr/shell/app_sdk/__init__.py
tgzr/shell/app_sdk/_base_app.py
tgzr/shell/app_sdk/app_info.py
tgzr/shell/app_sdk/exceptions.py
tgzr/shell/app_sdk/exe_app.py
tgzr/shell/app_sdk/host_app.py
tgzr/shell/app_sdk/nice_app.py
tgzr/shell/app_sdk/qtpy_app.py
tgzr/shell/app_sdk/tgzr_icon.png
tgzr/shell/app_sdk/nice_app_template/__init__.py
tgzr/shell/app_sdk/nice_app_template/app.py
tgzr/shell/app_sdk/nice_app_template/run_dev.py
tgzr/shell/app_sdk/nice_app_template/run_native.py
tgzr/shell/app_sdk/nice_app_template/pages/__init__.py
tgzr/shell/cli_plugin/__init__.py
tgzr/shell/cli_plugin/app_cli.py
tgzr/shell/cli_plugin/dev_cli.py
tgzr/shell/cli_plugin/help_cli.py
tgzr/shell/cli_plugin/plugins_cli.py
tgzr/shell/cli_plugin/project_cli.py
tgzr/shell/cli_plugin/session_cli.py
tgzr/shell/cli_plugin/settings_cli.py
tgzr/shell/cli_plugin/studio_cli.py
tgzr/shell/cli_plugin/utils.py
tgzr/shell/cli_plugin/workspace_cli.py
tgzr/shell/connection_plugins/__init__.py
tgzr/shell/connection_plugins/default_connection.py
tgzr/shell/connection_plugins/tgzr_org.py
tgzr/shell/doc_app/__init__.py
tgzr/shell/doc_app/app.py
tgzr/shell/doc_app/run_dev.py
tgzr/shell/doc_app/run_native.py
tgzr/shell/doc_app/pages/__init__.py
tgzr/shell/system_apps/__init__.py
tgzr/shell/system_apps/register.py
tgzr/shell/system_apps/run_open.py
tgzr/shell/system_apps/run_terminal.py
tgzr_shell-0.102.dist-info/METADATA
tgzr_shell-0.102.dist-info/WHEEL
tgzr_shell-0.102.dist-info/entry_points.txt
tgzr_shell-0.102.dist-info/licenses/LICENSE
tgzr_shell-0.102.dist-info/RECORD
