Metadata-Version: 2.4
Name: tgzr.shell
Version: 0.102
Summary: tgzr command line interface
Project-URL: Documentation, https://github.com/open-tgzr/tgzr.shell#readme
Project-URL: Issues, https://github.com/open-tgzr/tgzr.shell/issues
Project-URL: Source, https://github.com/open-tgzr/tgzr.shell
Author-email: Dee <dee.sometech@gmail.com>
License-Expression: GPL-3.0-or-later
License-File: LICENSE
Classifier: Development Status :: 4 - Beta
Classifier: Programming Language :: Python
Classifier: Programming Language :: Python :: 3.8
Classifier: Programming Language :: Python :: 3.9
Classifier: Programming Language :: Python :: 3.10
Classifier: Programming Language :: Python :: 3.11
Classifier: Programming Language :: Python :: 3.12
Classifier: Programming Language :: Python :: Implementation :: CPython
Classifier: Programming Language :: Python :: Implementation :: PyPy
Requires-Python: >=3.9
Requires-Dist: eval-type-backport
Requires-Dist: pydantic-settings>=2.8.1
Requires-Dist: tgzr-cli>=0.100
Requires-Dist: tgzr-nice>=0.100
Requires-Dist: tgzr-package-management>=0.100
Requires-Dist: tgzr-shell-brokers-jsbroker>=0.100
Requires-Dist: tgzr-shell-services-settings>=0.100
Provides-Extra: nicegui
Requires-Dist: nicegui>=2.24.2; extra == 'nicegui'
Requires-Dist: pywebview[qt]>=6.1; extra == 'nicegui'
Requires-Dist: tgzr-nice>=0.100; extra == 'nicegui'
Provides-Extra: qt
Requires-Dist: pyside6>=6.6.3.1; extra == 'qt'
Requires-Dist: qtpy>=2.4.3; extra == 'qt'
